{
  "actions" : [ {
    "module" : "init",
    "date" : "2024-11-30T19:31:23.282460500Z",
    "properties" : {
      "packageName" : "com.jsorant.personaljourney",
      "projectName" : "Personal Journey",
      "baseName" : "personalJourney",
      "endOfLine" : "lf",
      "indentSize" : 2,
      "springConfigurationFormat" : "yaml"
    }
  }, {
    "module" : "application-service-hexagonal-architecture-documentation",
    "date" : "2024-11-30T19:31:23.763393800Z",
    "properties" : {
      "packageName" : "com.jsorant.personaljourney",
      "projectName" : "Personal Journey",
      "baseName" : "personalJourney",
      "endOfLine" : "lf",
      "indentSize" : 2,
      "springConfigurationFormat" : "yaml"
    }
  }, {
    "module" : "renovate",
    "date" : "2024-11-30T19:31:24.373284100Z",
    "properties" : {
      "packageName" : "com.jsorant.personaljourney",
      "projectName" : "Personal Journey",
      "baseName" : "personalJourney",
      "endOfLine" : "lf",
      "indentSize" : 2,
      "springConfigurationFormat" : "yaml"
    }
  }, {
    "module" : "maven-java",
    "date" : "2024-11-30T19:31:25.191254600Z",
    "properties" : {
      "packageName" : "com.jsorant.personaljourney",
      "projectName" : "Personal Journey",
      "baseName" : "personalJourney",
      "endOfLine" : "lf",
      "indentSize" : 2,
      "springConfigurationFormat" : "yaml"
    }
  } ]
}